mcsas3gui/__init__.py
mcsas3gui/__main__.py
mcsas3gui/configurations/histogram/hist_config_dual.yaml
mcsas3gui/configurations/histogram/hist_config_mono.yaml
mcsas3gui/configurations/prefab/advanced_nexus_demo.yaml
mcsas3gui/configurations/prefab/getting_started.yaml
mcsas3gui/configurations/prefab/nPSize4_example.yaml
mcsas3gui/configurations/prefab/quick_start_demo.yaml
mcsas3gui/configurations/prefab/round_robin_dataset_1.yaml
mcsas3gui/configurations/prefab/round_robin_dataset_3.yaml
mcsas3gui/configurations/readdata/read_csv_simple.yaml
mcsas3gui/configurations/readdata/read_many.yaml
mcsas3gui/configurations/readdata/read_nxs_simple.yaml
mcsas3gui/configurations/readdata/read_nxs_with_omit.yaml
mcsas3gui/configurations/readdata/read_pdh.yaml
mcsas3gui/configurations/run/run_config_sphere_at_hardsphere.yaml
mcsas3gui/configurations/run/run_config_spheres.yaml
mcsas3gui/configurations/run/run_config_spheres_auto.yaml
mcsas3gui/gui/__init__.py
mcsas3gui/gui/data_loading_tab.py
mcsas3gui/gui/file_line_selection_widget.py
mcsas3gui/gui/file_selection_widget.py
mcsas3gui/gui/getting_started_tab.py
mcsas3gui/gui/hist_run_tab.py
mcsas3gui/gui/hist_settings_tab.py
mcsas3gui/gui/main_window.py
mcsas3gui/gui/optimization_tab.py
mcsas3gui/gui/run_settings_tab.py
mcsas3gui/gui/yaml_editor_widget.py
mcsas3gui/resources/logo/mcsas3.svg
mcsas3gui/testdata/merged_AutoMOFs_7_L011.nxs
mcsas3gui/testdata/nPSize4.dat
mcsas3gui/testdata/quickstartdemo1.csv
mcsas3gui/testdata/round_robin_dataset_1.dat
mcsas3gui/testdata/round_robin_dataset_2.dat
mcsas3gui/testdata/round_robin_dataset_3.dat
mcsas3gui/testdata/round_robin_dataset_4.dat
mcsas3gui/utils/__init__.py
mcsas3gui/utils/base_worker.py
mcsas3gui/utils/file_utils.py
mcsas3gui/utils/logging_config.py
mcsas3gui/utils/task_runner_mixin.py
mcsas3gui/utils/yaml_syntax_highlighter.py
mcsas3gui/utils/yaml_utils.py
mcsas3gui-0.1.6.dist-info/licenses/AUTHORS.rst
mcsas3gui-0.1.6.dist-info/licenses/LICENSE
mcsas3gui-0.1.6.dist-info/licenses/LICENSE.txt
mcsas3gui-0.1.6.dist-info/METADATA
mcsas3gui-0.1.6.dist-info/WHEEL
mcsas3gui-0.1.6.dist-info/entry_points.txt
mcsas3gui-0.1.6.dist-info/top_level.txt
mcsas3gui-0.1.6.dist-info/RECORD
