Metadata-Version: 2.4
Name: McSAS3GUI
Version: 0.1.6
Summary: A graphical user interface for the McSAS3 software.
Author-email: "Brian R. Pauw" <brian.pauw@bam.de>, Ingo Breßler <ingo.bressler@bam.de>
License-Expression: MIT
Project-URL: homepage, https://BAMresearch.github.io/mcsas3gui
Project-URL: documentation, https://BAMresearch.github.io/mcsas3gui
Project-URL: repository, https://github.com/BAMresearch/mcsas3gui
Project-URL: changelog, https://BAMresearch.github.io/mcsas3gui/changelog.html
Classifier: Development Status :: 4 - Beta
Classifier: Operating System :: Unix
Classifier: Operating System :: POSIX
Classifier: Operating System :: MacOS
Classifier: Operating System :: Microsoft :: Windows
Classifier: Programming Language :: Python
Classifier: Programming Language :: Python :: 3
Classifier: Programming Language :: Python :: 3 :: Only
Classifier: Programming Language :: Python :: 3.12
Classifier: Programming Language :: Python :: Implementation :: CPython
Classifier: Topic :: Utilities
Classifier: Topic :: Scientific/Engineering
Classifier: Intended Audience :: Developers
Classifier: Intended Audience :: Science/Research
License-File: LICENSE
License-File: LICENSE.txt
License-File: AUTHORS.rst
Requires-Dist: PyQt6>=6.7.1
Requires-Dist: mcsas3
Dynamic: license-file
